bean_rs-0.3.1.dist-info/METADATA
bean_rs-0.3.1.dist-info/WHEEL
bean_rs-0.3.1.dist-info/license_files/LICENSE
bean_rs/bean_rs.pyi
bean_rs/py.typed
bean_rs/__init__.py
bean_rs/_bean_rs.pypy39-pp73-x86_64-linux-gnu.so
bean_rs-0.3.1.dist-info/RECORD
