Metadata-Version: 2.3
Name: bean-rs
Version: 0.3.1
Classifier: Environment :: Console
Classifier: License :: OSI Approved :: MIT License
Classifier: Operating System :: Unix
Classifier: Programming Language :: Rust
Classifier: Programming Language :: Python
Classifier: Programming Language :: Python :: Implementation :: CPython
License-File: LICENSE
Summary: beancount clone in Rust
Author: Chris Arderne <chris@rdrn.me
Author-email: Chris Arderne <chris@rdrn.me
License: MIT
Requires-Python: >=3.9
Project-URL: homepage, https://github.com/carderne/signal-export
Project-URL: repository, https://github.com/carderne/signal-export
